Workbook

Sheet Como usar
A1: Catálogo de aluguel — Ateline Ateliê
A3: Texto azul = você preenche. Texto preto = fórmula automática (não editar).
A4: Bolos: uma linha por PEÇA física, com andares mín. e máx. O status fica aqui.
A5: Opções de aluguel: uma linha por combinação de decoração + andares (JARDIM_001_FLORES_3A, JARDIM_001_BORBOLETAS_4A).
A6: O status vem do bolo: alugou qualquer opção → marque o bolo como Alugado e TODAS as opções saem do site.
A7: Andar avulso: as 2 bases douradas, uma linha por unidade, cada uma com status próprio.
A8: Para usar a base num bolo, marque 'Aceita base dourada? = Sim' na aba Bolos.
A9: Personalização (nome/idade) já está inclusa no aluguel. O nome e a idade do cliente vão no pedido.
A10: Topos: Fixo = já incluso · Opcional = cliente escolhe da aba Topos · Sem topo.
A11: Em manutenção = chegou avariado. Preencha Previsão de volta e Obs. manutenção.
A12: Códigos sem acento e sem espaço, 3 dígitos, nunca reaproveitar. Linhas de exemplo têm preços fictícios.
A13: Só a inicial: em 'Personalização', escolha Inicial quando o bolo aceita apenas a inicial do aniversariante.
A14: Refazer: bolo Inativo (a peça não existe mais, só a foto) com 'Pode ser refeito? = Sim' aparece no site como primeira locação. O preço é o de encomenda nova (coluna 'Preço encomenda nova' da aba Opções de aluguel), e a cliente ganha o desconto digitando o cupom configurado abaixo. Pedido com no mínimo 20 dias de antecedência da festa.
A15: Resumo | B15: Bolos | C15: Topos | D15: Andar avulso
A16: Disponível | B16: =COUNTIF(Bolos!$J:$J,A16) -> 1 | C16: =COUNTIF(Topos!$E:$E,A16) -> 1 | D16: =COUNTIF('Andar avulso'!$E:$E,A16) -> 2
A17: Alugado | B17: =COUNTIF(Bolos!$J:$J,A17) -> 0 | C17: =COUNTIF(Topos!$E:$E,A17) -> 1 | D17: =COUNTIF('Andar avulso'!$E:$E,A17) -> 0
A18: Em manutenção | B18: =COUNTIF(Bolos!$J:$J,A18) -> 1 | C18: =COUNTIF(Topos!$E:$E,A18) -> 0 | D18: =COUNTIF('Andar avulso'!$E:$E,A18) -> 0
A19: Inativo | B19: =COUNTIF(Bolos!$J:$J,A19) -> 0 | C19: =COUNTIF(Topos!$E:$E,A19) -> 0 | D19: =COUNTIF('Andar avulso'!$E:$E,A19) -> 0
A20: Total | B20: =SUM(B16:B19) -> 2 | C20: =SUM(C16:C19) -> 2 | D20: =SUM(D16:D19) -> 2
A22: Inativos que podem ser refeitos | B22: =COUNTIFS(Bolos!$J:$J,"Inativo",Bolos!$O:$O,"Sim") -> 0
A24: Cupom para bolos refeitos
A25: Código do cupom | B25: REFAZ30
A26: Desconto | B26: 0.3
A28: Venda: preencha 'Preço venda (R$)' em todas as opções. O site mostra o preço de aluguel e o de venda em todas as peças. Venda tem envio para todo o Brasil; aluguel é só com retirada no Rio.

Sheet Bolos
A1: Código do bolo | B1: Nome | C1: Tema | D1: Andares mín. | E1: Andares máx. | F1: Tipo de topo | G1: Topos compatíveis | H1: Aceita base dourada? | I1: Personalização (inclusa no aluguel) | J1: Status | K1: Previsão de volta | L1: Obs. manutenção | M1: Fotos (link) | N1: Observações | O1: Pode ser refeito?
A2: SAFARI_001 | B2: Safari | C2: Safari | D2: 3 | E2: 5 | F2: Fixo | H2: Sim | I2: Nome e idade | J2: Disponível
A3: JARDIM_001 | B3: Jardim encantado | C3: Jardim | D3: 3 | E3: 4 | F3: Opcional | G3: TOPO_001, TOPO_003 | H3: Sim | I3: Nome | J3: Em manutenção | K3: 46323 | L3: Borboleta do 2º andar descolou

Sheet Opções de aluguel
A1: Código da opção | B1: Código do bolo | C1: Decoração | D1: Andares | E1: Nome no site | F1: Preço aluguel (R$) | G1: Status do bolo | H1: Aparece disponível no site? | I1: Andares dentro do limite? | J1: Fotos da opção (link) | K1: Preço encomenda nova (R$) | L1: Preço com cupom (R$) | M1: Aparece como 'refazer' no site? | N1: Preço venda (R$)
A2: SAFARI_001_3A | B2: SAFARI_001 | D2: 3 | E2: =IF(B2="","",IFERROR(INDEX(Bolos!$B:$B,MATCH(B2,Bolos!$A:$A,0))&IF(C2="",""," — "&C2)&" — "&D2&" andares","")) -> Safari — 3 andares | F2: 150 | G2: =IF(B2="","",IFERROR(INDEX(Bolos!$J:$J,MATCH(B2,Bolos!$A:$A,0)),"Código não encontrado")) -> Disponível | H2: =IF(B2="","",IF(G2="Disponível","Sim","Não")) -> Sim | I2: =IF(OR(B2="",D2=""),"",IFERROR(IF(AND(D2>=INDEX(Bolos!$D:$D,MATCH(B2,Bolos!$A:$A,0)),D2<=INDEX(Bolos!$E:$E,MATCH(B2,Bolos!$A:$A,0))),"OK","Fora do limite"),"")) -> OK | L2: =IF(K2="","",ROUND(K2*(1-'Como usar'!$B$26),2)) | M2: =IF(B2="","",IF(AND(G2="Inativo",IFERROR(INDEX(Bolos!$O:$O,MATCH(B2,Bolos!$A:$A,0)),"")="Sim",K2<>""),"Sim","Não")) -> Não
A3: SAFARI_001_4A | B3: SAFARI_001 | D3: 4 | E3: =IF(B3="","",IFERROR(INDEX(Bolos!$B:$B,MATCH(B3,Bolos!$A:$A,0))&IF(C3="",""," — "&C3)&" — "&D3&" andares","")) -> Safari — 4 andares | F3: 180 | G3: =IF(B3="","",IFERROR(INDEX(Bolos!$J:$J,MATCH(B3,Bolos!$A:$A,0)),"Código não encontrado")) -> Disponível | H3: =IF(B3="","",IF(G3="Disponível","Sim","Não")) -> Sim | I3: =IF(OR(B3="",D3=""),"",IFERROR(IF(AND(D3>=INDEX(Bolos!$D:$D,MATCH(B3,Bolos!$A:$A,0)),D3<=INDEX(Bolos!$E:$E,MATCH(B3,Bolos!$A:$A,0))),"OK","Fora do limite"),"")) -> OK | L3: =IF(K3="","",ROUND(K3*(1-'Como usar'!$B$26),2)) | M3: =IF(B3="","",IF(AND(G3="Inativo",IFERROR(INDEX(Bolos!$O:$O,MATCH(B3,Bolos!$A:$A,0)),"")="Sim",K3<>""),"Sim","Não")) -> Não
A4: SAFARI_001_5A | B4: SAFARI_001 | D4: 5 | E4: =IF(B4="","",IFERROR(INDEX(Bolos!$B:$B,MATCH(B4,Bolos!$A:$A,0))&IF(C4="",""," — "&C4)&" — "&D4&" andares","")) -> Safari — 5 andares | F4: 210 | G4: =IF(B4="","",IFERROR(INDEX(Bolos!$J:$J,MATCH(B4,Bolos!$A:$A,0)),"Código não encontrado")) -> Disponível | H4: =IF(B4="","",IF(G4="Disponível","Sim","Não")) -> Sim | I4: =IF(OR(B4="",D4=""),"",IFERROR(IF(AND(D4>=INDEX(Bolos!$D:$D,MATCH(B4,Bolos!$A:$A,0)),D4<=INDEX(Bolos!$E:$E,MATCH(B4,Bolos!$A:$A,0))),"OK","Fora do limite"),"")) -> OK | L4: =IF(K4="","",ROUND(K4*(1-'Como usar'!$B$26),2)) | M4: =IF(B4="","",IF(AND(G4="Inativo",IFERROR(INDEX(Bolos!$O:$O,MATCH(B4,Bolos!$A:$A,0)),"")="Sim",K4<>""),"Sim","Não")) -> Não
A5: JARDIM_001_FLORES_3A | B5: JARDIM_001 | C5: Flores | D5: 3 | E5: =IF(B5="","",IFERROR(INDEX(Bolos!$B:$B,MATCH(B5,Bolos!$A:$A,0))&IF(C5="",""," — "&C5)&" — "&D5&" andares","")) -> Jardim encantado — Flores — 3 andares | F5: 140 | G5: =IF(B5="","",IFERROR(INDEX(Bolos!$J:$J,MATCH(B5,Bolos!$A:$A,0)),"Código não encontrado")) -> Em manutenção | H5: =IF(B5="","",IF(G5="Disponível","Sim","Não")) -> Não | I5: =IF(OR(B5="",D5=""),"",IFERROR(IF(AND(D5>=INDEX(Bolos!$D:$D,MATCH(B5,Bolos!$A:$A,0)),D5<=INDEX(Bolos!$E:$E,MATCH(B5,Bolos!$A:$A,0))),"OK","Fora do limite"),"")) -> OK | L5: =IF(K5="","",ROUND(K5*(1-'Como usar'!$B$26),2)) | M5: =IF(B5="","",IF(AND(G5="Inativo",IFERROR(INDEX(Bolos!$O:$O,MATCH(B5,Bolos!$A:$A,0)),"")="Sim",K5<>""),"Sim","Não")) -> Não
A6: JARDIM_001_BORBOLETAS_3A | B6: JARDIM_001 | C6: Borboletas | D6: 3 | E6: =IF(B6="","",IFERROR(INDEX(Bolos!$B:$B,MATCH(B6,Bolos!$A:$A,0))&IF(C6="",""," — "&C6)&" — "&D6&" andares","")) -> Jardim encantado — Borboletas — 3 andares | F6: 140 | G6: =IF(B6="","",IFERROR(INDEX(Bolos!$J:$J,MATCH(B6,Bolos!$A:$A,0)),"Código não encontrado")) -> Em manutenção | H6: =IF(B6="","",IF(G6="Disponível","Sim","Não")) -> Não | I6: =IF(OR(B6="",D6=""),"",IFERROR(IF(AND(D6>=INDEX(Bolos!$D:$D,MATCH(B6,Bolos!$A:$A,0)),D6<=INDEX(Bolos!$E:$E,MATCH(B6,Bolos!$A:$A,0))),"OK","Fora do limite"),"")) -> OK | L6: =IF(K6="","",ROUND(K6*(1-'Como usar'!$B$26),2)) | M6: =IF(B6="","",IF(AND(G6="Inativo",IFERROR(INDEX(Bolos!$O:$O,MATCH(B6,Bolos!$A:$A,0)),"")="Sim",K6<>""),"Sim","Não")) -> Não
A7: JARDIM_001_BORBOLETAS_4A | B7: JARDIM_001 | C7: Borboletas | D7: 4 | E7: =IF(B7="","",IFERROR(INDEX(Bolos!$B:$B,MATCH(B7,Bolos!$A:$A,0))&IF(C7="",""," — "&C7)&" — "&D7&" andares","")) -> Jardim encantado — Borboletas — 4 andares | F7: 170 | G7: =IF(B7="","",IFERROR(INDEX(Bolos!$J:$J,MATCH(B7,Bolos!$A:$A,0)),"Código não encontrado")) -> Em manutenção | H7: =IF(B7="","",IF(G7="Disponível","Sim","Não")) -> Não | I7: =IF(OR(B7="",D7=""),"",IFERROR(IF(AND(D7>=INDEX(Bolos!$D:$D,MATCH(B7,Bolos!$A:$A,0)),D7<=INDEX(Bolos!$E:$E,MATCH(B7,Bolos!$A:$A,0))),"OK","Fora do limite"),"")) -> OK | L7: =IF(K7="","",ROUND(K7*(1-'Como usar'!$B$26),2)) | M7: =IF(B7="","",IF(AND(G7="Inativo",IFERROR(INDEX(Bolos!$O:$O,MATCH(B7,Bolos!$A:$A,0)),"")="Sim",K7<>""),"Sim","Não")) -> Não
E8: =IF(B8="","",IFERROR(INDEX(Bolos!$B:$B,MATCH(B8,Bolos!$A:$A,0))&IF(C8="",""," — "&C8)&" — "&D8&" andares","")) | G8: =IF(B8="","",IFERROR(INDEX(Bolos!$J:$J,MATCH(B8,Bolos!$A:$A,0)),"Código não encontrado")) | H8: =IF(B8="","",IF(G8="Disponível","Sim","Não")) | I8: =IF(OR(B8="",D8=""),"",IFERROR(IF(AND(D8>=INDEX(Bolos!$D:$D,MATCH(B8,Bolos!$A:$A,0)),D8<=INDEX(Bolos!$E:$E,MATCH(B8,Bolos!$A:$A,0))),"OK","Fora do limite"),"")) | L8: =IF(K8="","",ROUND(K8*(1-'Como usar'!$B$26),2)) | M8: =IF(B8="","",IF(AND(G8="Inativo",IFERROR(INDEX(Bolos!$O:$O,MATCH(B8,Bolos!$A:$A,0)),"")="Sim",K8<>""),"Sim","Não"))
E9: =IF(B9="","",IFERROR(INDEX(Bolos!$B:$B,MATCH(B9,Bolos!$A:$A,0))&IF(C9="",""," — "&C9)&" — "&D9&" andares","")) | G9: =IF(B9="","",IFERROR(INDEX(Bolos!$J:$J,MATCH(B9,Bolos!$A:$A,0)),"Código não encontrado")) | H9: =IF(B9="","",IF(G9="Disponível","Sim","Não")) | I9: =IF(OR(B9="",D9=""),"",IFERROR(IF(AND(D9>=INDEX(Bolos!$D:$D,MATCH(B9,Bolos!$A:$A,0)),D9<=INDEX(Bolos!$E:$E,MATCH(B9,Bolos!$A:$A,0))),"OK","Fora do limite"),"")) | L9: =IF(K9="","",ROUND(K9*(1-'Como usar'!$B$26),2)) | M9: =IF(B9="","",IF(AND(G9="Inativo",IFERROR(INDEX(Bolos!$O:$O,MATCH(B9,Bolos!$A:$A,0)),"")="Sim",K9<>""),"Sim","Não"))
E10: =IF(B10="","",IFERROR(INDEX(Bolos!$B:$B,MATCH(B10,Bolos!$A:$A,0))&IF(C10="",""," — "&C10)&" — "&D10&" andares","")) | G10: =IF(B10="","",IFERROR(INDEX(Bolos!$J:$J,MATCH(B10,Bolos!$A:$A,0)),"Código não encontrado")) | H10: =IF(B10="","",IF(G10="Disponível","Sim","Não")) | I10: =IF(OR(B10="",D10=""),"",IFERROR(IF(AND(D10>=INDEX(Bolos!$D:$D,MATCH(B10,Bolos!$A:$A,0)),D10<=INDEX(Bolos!$E:$E,MATCH(B10,Bolos!$A:$A,0))),"OK","Fora do limite"),"")) | L10: =IF(K10="","",ROUND(K10*(1-'Como usar'!$B$26),2)) | M10: =IF(B10="","",IF(AND(G10="Inativo",IFERROR(INDEX(Bolos!$O:$O,MATCH(B10,Bolos!$A:$A,0)),"")="Sim",K10<>""),"Sim","Não"))
E11: =IF(B11="","",IFERROR(INDEX(Bolos!$B:$B,MATCH(B11,Bolos!$A:$A,0))&IF(C11="",""," — "&C11)&" — "&D11&" andares","")) | G11: =IF(B11="","",IFERROR(INDEX(Bolos!$J:$J,MATCH(B11,Bolos!$A:$A,0)),"Código não encontrado")) | H11: =IF(B11="","",IF(G11="Disponível","Sim","Não")) | I11: =IF(OR(B11="",D11=""),"",IFERROR(IF(AND(D11>=INDEX(Bolos!$D:$D,MATCH(B11,Bolos!$A:$A,0)),D11<=INDEX(Bolos!$E:$E,MATCH(B11,Bolos!$A:$A,0))),"OK","Fora do limite"),"")) | L11: =IF(K11="","",ROUND(K11*(1-'Como usar'!$B$26),2)) | M11: =IF(B11="","",IF(AND(G11="Inativo",IFERROR(INDEX(Bolos!$O:$O,MATCH(B11,Bolos!$A:$A,0)),"")="Sim",K11<>""),"Sim","Não"))
E12: =IF(B12="","",IFERROR(INDEX(Bolos!$B:$B,MATCH(B12,Bolos!$A:$A,0))&IF(C12="",""," — "&C12)&" — "&D12&" andares","")) | G12: =IF(B12="","",IFERROR(INDEX(Bolos!$J:$J,MATCH(B12,Bolos!$A:$A,0)),"Código não encontrado")) | H12: =IF(B12="","",IF(G12="Disponível","Sim","Não")) | I12: =IF(OR(B12="",D12=""),"",IFERROR(IF(AND(D12>=INDEX(Bolos!$D:$D,MATCH(B12,Bolos!$A:$A,0)),D12<=INDEX(Bolos!$E:$E,MATCH(B12,Bolos!$A:$A,0))),"OK","Fora do limite"),"")) | L12: =IF(K12="","",ROUND(K12*(1-'Como usar'!$B$26),2)) | M12: =IF(B12="","",IF(AND(G12="Inativo",IFERROR(INDEX(Bolos!$O:$O,MATCH(B12,Bolos!$A:$A,0)),"")="Sim",K12<>""),"Sim","Não"))
E13: =IF(B13="","",IFERROR(INDEX(Bolos!$B:$B,MATCH(B13,Bolos!$A:$A,0))&IF(C13="",""," — "&C13)&" — "&D13&" andares","")) | G13: =IF(B13="","",IFERROR(INDEX(Bolos!$J:$J,MATCH(B13,Bolos!$A:$A,0)),"Código não encontrado")) | H13: =IF(B13="","",IF(G13="Disponível","Sim","Não")) | I13: =IF(OR(B13="",D13=""),"",IFERROR(IF(AND(D13>=INDEX(Bolos!$D:$D,MATCH(B13,Bolos!$A:$A,0)),D13<=INDEX(Bolos!$E:$E,MATCH(B13,Bolos!$A:$A,0))),"OK","Fora do limite"),"")) | L13: =IF(K13="","",ROUND(K13*(1-'Como usar'!$B$26),2)) | M13: =IF(B13="","",IF(AND(G13="Inativo",IFERROR(INDEX(Bolos!$O:$O,MATCH(B13,Bolos!$A:$A,0)),"")="Sim",K13<>""),"Sim","Não"))
E14: =IF(B14="","",IFERROR(INDEX(Bolos!$B:$B,MATCH(B14,Bolos!$A:$A,0))&IF(C14="",""," — "&C14)&" — "&D14&" andares","")) | G14: =IF(B14="","",IFERROR(INDEX(Bolos!$J:$J,MATCH(B14,Bolos!$A:$A,0)),"Código não encontrado")) | H14: =IF(B14="","",IF(G14="Disponível","Sim","Não")) | I14: =IF(OR(B14="",D14=""),"",IFERROR(IF(AND(D14>=INDEX(Bolos!$D:$D,MATCH(B14,Bolos!$A:$A,0)),D14<=INDEX(Bolos!$E:$E,MATCH(B14,Bolos!$A:$A,0))),"OK","Fora do limite"),"")) | L14: =IF(K14="","",ROUND(K14*(1-'Como usar'!$B$26),2)) | M14: =IF(B14="","",IF(AND(G14="Inativo",IFERROR(INDEX(Bolos!$O:$O,MATCH(B14,Bolos!$A:$A,0)),"")="Sim",K14<>""),"Sim","Não"))
E15: =IF(B15="","",IFERROR(INDEX(Bolos!$B:$B,MATCH(B15,Bolos!$A:$A,0))&IF(C15="",""," — "&C15)&" — "&D15&" andares","")) | G15: =IF(B15="","",IFERROR(INDEX(Bolos!$J:$J,MATCH(B15,Bolos!$A:$A,0)),"Código não encontrado")) | H15: =IF(B15="","",IF(G15="Disponível","Sim","Não")) | I15: =IF(OR(B15="",D15=""),"",IFERROR(IF(AND(D15>=INDEX(Bolos!$D:$D,MATCH(B15,Bolos!$A:$A,0)),D15<=INDEX(Bolos!$E:$E,MATCH(B15,Bolos!$A:$A,0))),"OK","Fora do limite"),"")) | L15: =IF(K15="","",ROUND(K15*(1-'Como usar'!$B$26),2)) | M15: =IF(B15="","",IF(AND(G15="Inativo",IFERROR(INDEX(Bolos!$O:$O,MATCH(B15,Bolos!$A:$A,0)),"")="Sim",K15<>""),"Sim","Não"))
E16: =IF(B16="","",IFERROR(INDEX(Bolos!$B:$B,MATCH(B16,Bolos!$A:$A,0))&IF(C16="",""," — "&C16)&" — "&D16&" andares","")) | G16: =IF(B16="","",IFERROR(INDEX(Bolos!$J:$J,MATCH(B16,Bolos!$A:$A,0)),"Código não encontrado")) | H16: =IF(B16="","",IF(G16="Disponível","Sim","Não")) | I16: =IF(OR(B16="",D16=""),"",IFERROR(IF(AND(D16>=INDEX(Bolos!$D:$D,MATCH(B16,Bolos!$A:$A,0)),D16<=INDEX(Bolos!$E:$E,MATCH(B16,Bolos!$A:$A,0))),"OK","Fora do limite"),"")) | L16: =IF(K16="","",ROUND(K16*(1-'Como usar'!$B$26),2)) | M16: =IF(B16="","",IF(AND(G16="Inativo",IFERROR(INDEX(Bolos!$O:$O,MATCH(B16,Bolos!$A:$A,0)),"")="Sim",K16<>""),"Sim","Não"))
E17: =IF(B17="","",IFERROR(INDEX(Bolos!$B:$B,MATCH(B17,Bolos!$A:$A,0))&IF(C17="",""," — "&C17)&" — "&D17&" andares","")) | G17: =IF(B17="","",IFERROR(INDEX(Bolos!$J:$J,MATCH(B17,Bolos!$A:$A,0)),"Código não encontrado")) | H17: =IF(B17="","",IF(G17="Disponível","Sim","Não")) | I17: =IF(OR(B17="",D17=""),"",IFERROR(IF(AND(D17>=INDEX(Bolos!$D:$D,MATCH(B17,Bolos!$A:$A,0)),D17<=INDEX(Bolos!$E:$E,MATCH(B17,Bolos!$A:$A,0))),"OK","Fora do limite"),"")) | L17: =IF(K17="","",ROUND(K17*(1-'Como usar'!$B$26),2)) | M17: =IF(B17="","",IF(AND(G17="Inativo",IFERROR(INDEX(Bolos!$O:$O,MATCH(B17,Bolos!$A:$A,0)),"")="Sim",K17<>""),"Sim","Não"))
E18: =IF(B18="","",IFERROR(INDEX(Bolos!$B:$B,MATCH(B18,Bolos!$A:$A,0))&IF(C18="",""," — "&C18)&" — "&D18&" andares","")) | G18: =IF(B18="","",IFERROR(INDEX(Bolos!$J:$J,MATCH(B18,Bolos!$A:$A,0)),"Código não encontrado")) | H18: =IF(B18="","",IF(G18="Disponível","Sim","Não")) | I18: =IF(OR(B18="",D18=""),"",IFERROR(IF(AND(D18>=INDEX(Bolos!$D:$D,MATCH(B18,Bolos!$A:$A,0)),D18<=INDEX(Bolos!$E:$E,MATCH(B18,Bolos!$A:$A,0))),"OK","Fora do limite"),"")) | L18: =IF(K18="","",ROUND(K18*(1-'Como usar'!$B$26),2)) | M18: =IF(B18="","",IF(AND(G18="Inativo",IFERROR(INDEX(Bolos!$O:$O,MATCH(B18,Bolos!$A:$A,0)),"")="Sim",K18<>""),"Sim","Não"))
E19: =IF(B19="","",IFERROR(INDEX(Bolos!$B:$B,MATCH(B19,Bolos!$A:$A,0))&IF(C19="",""," — "&C19)&" — "&D19&" andares","")) | G19: =IF(B19="","",IFERROR(INDEX(Bolos!$J:$J,MATCH(B19,Bolos!$A:$A,0)),"Código não encontrado")) | H19: =IF(B19="","",IF(G19="Disponível","Sim","Não")) | I19: =IF(OR(B19="",D19=""),"",IFERROR(IF(AND(D19>=INDEX(Bolos!$D:$D,MATCH(B19,Bolos!$A:$A,0)),D19<=INDEX(Bolos!$E:$E,MATCH(B19,Bolos!$A:$A,0))),"OK","Fora do limite"),"")) | L19: =IF(K19="","",ROUND(K19*(1-'Como usar'!$B$26),2)) | M19: =IF(B19="","",IF(AND(G19="Inativo",IFERROR(INDEX(Bolos!$O:$O,MATCH(B19,Bolos!$A:$A,0)),"")="Sim",K19<>""),"Sim","Não"))
... E300: =IF(B300="","",IFERROR(INDEX(Bolos!$B:$B,MATCH(B300,Bolos!$A:$A,0))&IF(C300="",""," — "&C300)&" — "&D300&" andares","")) | G300: =IF(B300="","",IFERROR(INDEX(Bolos!$J:$J,MATCH(B300,Bolos!$A:$A,0)),"Código não encontrado")) | H300: =IF(B300="","",IF(G300="Disponível","Sim","Não")) | I300: =IF(OR(B300="",D300=""),"",IFERROR(IF(AND(D300>=INDEX(Bolos!$D:$D,MATCH(B300,Bolos!$A:$A,0)),D300<=INDEX(Bolos!$E:$E,MATCH(B300,Bolos!$A:$A,0))),"OK","Fora do limite"),"")) | L300: =IF(K300="","",ROUND(K300*(1-'Como usar'!$B$26),2)) | M300: =IF(B300="","",IF(AND(G300="Inativo",IFERROR(INDEX(Bolos!$O:$O,MATCH(B300,Bolos!$A:$A,0)),"")="Sim",K300<>""),"Sim","Não"))

Sheet Topos
A1: Código | B1: Nome | C1: Descrição | D1: Preço aluguel (R$) | E1: Status | F1: Previsão de volta | G1: Obs. manutenção | H1: Aparece disponível no site? | I1: Fotos (link)
A2: TOPO_001 | B2: Coroa dourada | C2: Coroa com brilho dourado | D2: 30 | E2: Disponível | H2: =IF(A2="","",IF(E2="Disponível","Sim","Não")) -> Sim
A3: TOPO_003 | B3: Laço rosa | C3: Laço de cetim rosa | D3: 25 | E3: Alugado | F3: 46320 | H3: =IF(A3="","",IF(E3="Disponível","Sim","Não")) -> Não
H4: =IF(A4="","",IF(E4="Disponível","Sim","Não"))
H5: =IF(A5="","",IF(E5="Disponível","Sim","Não"))
H6: =IF(A6="","",IF(E6="Disponível","Sim","Não"))
H7: =IF(A7="","",IF(E7="Disponível","Sim","Não"))
H8: =IF(A8="","",IF(E8="Disponível","Sim","Não"))
H9: =IF(A9="","",IF(E9="Disponível","Sim","Não"))
H10: =IF(A10="","",IF(E10="Disponível","Sim","Não"))
H11: =IF(A11="","",IF(E11="Disponível","Sim","Não"))
H12: =IF(A12="","",IF(E12="Disponível","Sim","Não"))
H13: =IF(A13="","",IF(E13="Disponível","Sim","Não"))
H14: =IF(A14="","",IF(E14="Disponível","Sim","Não"))
H15: =IF(A15="","",IF(E15="Disponível","Sim","Não"))
... H300: =IF(A300="","",IF(E300="Disponível","Sim","Não"))

Sheet Andar avulso
A1: Código da unidade | B1: Nome | C1: Descrição | D1: Preço aluguel (R$) | E1: Status | F1: Previsão de volta | G1: Obs. manutenção | H1: Fotos (link) | J1: Unidades disponíveis | K1: Aparece disponível no site?
A2: BASE_DOURADA_001 | B2: Base dourada | C2: Andar avulso dourado; entra como base para deixar o bolo maior | D2: 40 | E2: Disponível | J2: =COUNTIF($E:$E,"Disponível")&" de "&COUNTA($A$2:$A$300) -> 2 de 2 | K2: =IF(COUNTIF($E:$E,"Disponível")>0,"Sim","Não") -> Sim
A3: BASE_DOURADA_002 | B3: Base dourada | C3: Andar avulso dourado; entra como base para deixar o bolo maior | D3: 40 | E3: Disponível

Sheet Listas
A1: Status | B1: Tipo de topo | C1: Sim/Não | D1: Personalização
A2: Disponível | B2: Fixo | C2: Sim | D2: Não
A3: Alugado | B3: Opcional | C3: Não | D3: Nome
A4: Em manutenção | B4: Sem topo | D4: Idade
A5: Inativo | D5: Nome e idade
D6: Inicial
